BasicPypiPackage/__init__.py
BasicPypiPackage-0.0.1.dist-info/METADATA
BasicPypiPackage-0.0.1.dist-info/WHEEL
BasicPypiPackage-0.0.1.dist-info/top_level.txt
BasicPypiPackage-0.0.1.dist-info/RECORD
