Metadata-Version: 2.1
Name: BasicPypiPackage
Version: 0.0.1
Summary: This is simple code for performing basic math operations.
Author: Yash
